[{"name": "Skhiri", "image": "https://cdn.futbin.com/content/fifa23/img/players/p67333990.png?v=23", "rating": 85, "stats": [{"PAC": "75", "SHO": "78", "PAS": "77", "DRI": "81", "DEF": "86", "PHY": "81"}]}, {"name": "Talbi", "image": "https://cdn.futbin.com/content/fifa23/img/players/p67354274.png?v=23", "rating": 84, "stats": [{"PAC": "79", "SHO": "45", "PAS": "66", "DRI": "73", "DEF": "83", "PHY": "83"}]}, {"name": "Sliti", "image": "https://cdn.futbin.com/content/fifa23/img/players/205257.png?v=23", "rating": 79, "stats": [{"PAC": "76", "SHO": "75", "PAS": "75", "DRI": "83", "DEF": "36", "PHY": "70"}]}, {"name": "Khazri", "image": "https://cdn.futbin.com/content/fifa23/img/players/194845.png?v=23", "rating": 79, "stats": [{"PAC": "73", "SHO": "82", "PAS": "78", "DRI": "80", "DEF": "45", "PHY": "73"}]}, {"name": "Sassi", "image": "https://cdn.futbin.com/content/fifa23/img/players/218215.png?v=23", "rating": 79, "stats": [{"PAC": "71", "SHO": "73", "PAS": "76", "DRI": "78", "DEF": "72", "PHY": "76"}]}, {"name": "Bronn", "image": "https://cdn.futbin.com/content/fifa23/img/players/235565.png?v=23", "rating": 78, "stats": [{"PAC": "69", "SHO": "66", "PAS": "72", "DRI": "66", "DEF": "78", "PHY": "79"}]}, {"name": "Jaziri", "image": "https://cdn.futbin.com/content/fifa23/img/players/268821.png?v=23", "rating": 78, "stats": [{"PAC": "77", "SHO": "79", "PAS": "62", "DRI": "77", "DEF": "35", "PHY": "71"}]}, {"name": "Abdi", "image": "https://cdn.futbin.com/content/fifa23/img/players/252711.png?v=23", "rating": 78, "stats": [{"PAC": "92", "SHO": "65", "PAS": "71", "DRI": "76", "DEF": "67", "PHY": "80"}]}, {"name": "Meriah", "image": "https://cdn.futbin.com/content/fifa23/img/players/241746.png?v=23", "rating": 78, "stats": [{"PAC": "75", "SHO": "56", "PAS": "57", "DRI": "63", "DEF": "76", "PHY": "80"}]}, {"name": "La\u00efdouni", "image": "https://cdn.futbin.com/content/fifa23/img/players/233642.png?v=23", "rating": 78, "stats": [{"PAC": "65", "SHO": "61", "PAS": "70", "DRI": "78", "DEF": "70", "PHY": "83"}]}, {"name": "Dr\u00e4ger", "image": "https://cdn.futbin.com/content/fifa23/img/players/242041.png?v=23", "rating": 78, "stats": [{"PAC": "88", "SHO": "70", "PAS": "69", "DRI": "77", "DEF": "71", "PHY": "69"}]}, {"name": "Khaoui", "image": "https://cdn.futbin.com/content/fifa23/img/players/220029.png?v=23", "rating": 78, "stats": [{"PAC": "68", "SHO": "75", "PAS": "78", "DRI": "79", "DEF": "52", "PHY": "65"}]}, {"name": "Mathlouthi", "image": "https://cdn.futbin.com/content/fifa23/img/players/241747.png?v=23", "rating": 78, "stats": [{"PAC": "86", "SHO": "66", "PAS": "71", "DRI": "78", "DEF": "70", "PHY": "78"}]}, {"name": "BenMustapha", "image": "https://cdn.futbin.com/content/fifa23/img/players/218216.png?v=23", "rating": 78, "stats": [{"DIV": "76", "HAN": "77", "KIC": "65", "REF": "75", "SPE": "52", "POS": "81"}]}, {"name": "Ma\u00e2loul", "image": "https://cdn.futbin.com/content/fifa23/img/players/218229.png?v=23", "rating": 78, "stats": [{"PAC": "81", "SHO": "73", "PAS": "75", "DRI": "78", "DEF": "71", "PHY": "70"}]}, {"name": "Khenissi", "image": "/design/img/blank_player.png", "rating": 78, "stats": [{"PAC": "80", "SHO": "79", "PAS": "68", "DRI": "80", "DEF": "33", "PHY": "65"}]}, {"name": "Bguir", "image": "/design/img/blank_player.png", "rating": 78, "stats": [{"PAC": "74", "SHO": "75", "PAS": "76", "DRI": "80", "DEF": "37", "PHY": "68"}]}, {"name": "Slimane", "image": "/design/img/blank_player.png", "rating": 77, "stats": [{"PAC": "74", "SHO": "66", "PAS": "71", "DRI": "78", "DEF": "64", "PHY": "80"}]}, {"name": "Zemzemi", "image": "/design/img/blank_player.png", "rating": 77, "stats": [{"PAC": "79", "SHO": "75", "PAS": "74", "DRI": "79", "DEF": "59", "PHY": "73"}]}, {"name": "Rafia", "image": "/design/img/blank_player.png", "rating": 77, "stats": [{"PAC": "72", "SHO": "74", "PAS": "75", "DRI": "79", "DEF": "38", "PHY": "66"}]}, {"name": "Ghandri", "image": "/design/img/blank_player.png", "rating": 77, "stats": [{"PAC": "45", "SHO": "45", "PAS": "61", "DRI": "55", "DEF": "75", "PHY": "87"}]}, {"name": "Jebali", "image": "/design/img/blank_player.png", "rating": 77, "stats": [{"PAC": "79", "SHO": "73", "PAS": "70", "DRI": "80", "DEF": "46", "PHY": "79"}]}, {"name": "BenYoussef", "image": "/design/img/blank_player.png", "rating": 77, "stats": [{"PAC": "84", "SHO": "77", "PAS": "70", "DRI": "75", "DEF": "41", "PHY": "82"}]}, {"name": "Jemal", "image": "/design/img/blank_player.png", "rating": 77, "stats": [{"DIV": "75", "HAN": "76", "KIC": "72", "REF": "72", "SPE": "30", "POS": "77"}]}, {"name": "Dahmen", "image": "/design/img/blank_player.png", "rating": 77, "stats": [{"DIV": "74", "HAN": "77", "KIC": "74", "REF": "73", "SPE": "25", "POS": "77"}]}, {"name": "Haddadi", "image": "/design/img/blank_player.png", "rating": 77, "stats": [{"PAC": "81", "SHO": "49", "PAS": "68", "DRI": "71", "DEF": "75", "PHY": "83"}]}, {"name": "Ifa", "image": "/design/img/blank_player.png", "rating": 77, "stats": [{"PAC": "69", "SHO": "38", "PAS": "60", "DRI": "52", "DEF": "79", "PHY": "79"}]}]